dexdata/__init__.py
dexdata/version.py
dexdata/configs/cfg.json
dexdata/dataset/__init__.py
dexdata/dataset/shadow/__init__.py
dexdata/dataset/standard/__init__.py
dexdata/dataset/stereo/__init__.py
dexdata/resource/__init__.py
dexdata/resource/d3model/__init__.py
dexdata/resource/d3model/abc/__init__.py
dexdata/resource/d3model/cad/__init__.py
dexdata/resource/d3model/objaverse/README.md
dexdata/resource/d3model/objaverse/__init__.py
dexdata/resource/d3model/objaverse/utils.py
dexdata/scripts/build.sh
dexdata/util/checker.py
dexdata/util/compare_objaverse.py
dexdata/util/minio_helper.py
dexdata/util/nas_downloader.py
dexdata/util/objaverse_to_minio.py
dexdata/util/parser.py
dexdata/util/uploader.py
dexdata/util/utils.py
dexsim_engine-0.1.0.dist-info/METADATA
dexsim_engine-0.1.0.dist-info/WHEEL
dexsim_engine-0.1.0.dist-info/top_level.txt
dexsim_engine-0.1.0.dist-info/RECORD
