Metadata-Version: 2.1
Name: dexsim-engine
Version: 0.1.0
Summary: DexData Python Lib is the SDK to download data asserts from dexforce data asserts management platform.
Home-page: 
Author: dexforce
Author-email: contact@dexforce.com
Classifier: Programming Language :: Python :: 3
Requires-Dist: minio (==7.2.3)
Requires-Dist: py7zr (==0.20.8)
Requires-Dist: tqdm (==4.65.0)
Requires-Dist: s3fs (==0.4.2)
Requires-Dist: requests (==2.31.0)
